[
  {
    "type": "attribute",
    "named": true,
    "fields": {},
    "children": {
      "multiple": true,
      "required": true,
      "types": [
        {
          "type": "attribute_name",
          "named": true
        },
        {
          "type": "attribute_value",
          "named": true
        },
        {
          "type": "quoted_attribute_value",
          "named": true
        }
      ]
    }
  },
  {
    "type": "cf_assignment",
    "named": true,
    "fields": {}
  },
  {
    "type": "cf_associative",
    "named": true,
    "fields": {},
    "children": {
      "multiple": true,
      "required": true,
      "types": [
        {
          "type": "cf_assignment",
          "named": true
        },
        {
          "type": "cf_associative",
          "named": true
        },
        {
          "type": "cf_comma",
          "named": true
        },
        {
          "type": "cf_operator",
          "named": true
        },
        {
          "type": "cf_parens",
          "named": true
        },
        {
          "type": "cf_period",
          "named": true
        },
        {
          "type": "cf_variable",
          "named": true
        }
      ]
    }
  },
  {
    "type": "cf_condition",
    "named": true,
    "fields": {}
  },
  {
    "type": "cf_else",
    "named": true,
    "fields": {},
    "children": {
      "multiple": true,
      "required": true,
      "types": [
        {
          "type": "cf_associative",
          "named": true
        },
        {
          "type": "cf_else_keyword",
          "named": true
        },
        {
          "type": "cf_hash",
          "named": true
        },
        {
          "type": "cf_parens",
          "named": true
        },
        {
          "type": "cf_tag",
          "named": true
        },
        {
          "type": "cf_tag_end",
          "named": true
        },
        {
          "type": "text",
          "named": true
        }
      ]
    }
  },
  {
    "type": "cf_elseif",
    "named": true,
    "fields": {},
    "children": {
      "multiple": true,
      "required": true,
      "types": [
        {
          "type": "cf_associative",
          "named": true
        },
        {
          "type": "cf_condition",
          "named": true
        },
        {
          "type": "cf_elseif_keyword",
          "named": true
        },
        {
          "type": "cf_hash",
          "named": true
        },
        {
          "type": "cf_parens",
          "named": true
        },
        {
          "type": "cf_tag",
          "named": true
        },
        {
          "type": "cf_tag_end",
          "named": true
        },
        {
          "type": "text",
          "named": true
        }
      ]
    }
  },
  {
    "type": "cf_function",
    "named": true,
    "fields": {},
    "children": {
      "multiple": true,
      "required": true,
      "types": [
        {
          "type": "attribute",
          "named": true
        },
        {
          "type": "cf_associative",
          "named": true
        },
        {
          "type": "cf_function_keyword",
          "named": true
        },
        {
          "type": "cf_hash",
          "named": true
        },
        {
          "type": "cf_parens",
          "named": true
        },
        {
          "type": "cf_tag",
          "named": true
        },
        {
          "type": "cf_tag_close",
          "named": true
        },
        {
          "type": "cf_tag_end",
          "named": true
        },
        {
          "type": "text",
          "named": true
        }
      ]
    }
  },
  {
    "type": "cf_hash",
    "named": true,
    "fields": {},
    "children": {
      "multiple": true,
      "required": true,
      "types": [
        {
          "type": "cf_assignment",
          "named": true
        },
        {
          "type": "cf_associative",
          "named": true
        },
        {
          "type": "cf_comma",
          "named": true
        },
        {
          "type": "cf_operator",
          "named": true
        },
        {
          "type": "cf_parens",
          "named": true
        },
        {
          "type": "cf_period",
          "named": true
        },
        {
          "type": "cf_variable",
          "named": true
        }
      ]
    }
  },
  {
    "type": "cf_if",
    "named": true,
    "fields": {},
    "children": {
      "multiple": true,
      "required": true,
      "types": [
        {
          "type": "cf_assignment",
          "named": true
        },
        {
          "type": "cf_associative",
          "named": true
        },
        {
          "type": "cf_comma",
          "named": true
        },
        {
          "type": "cf_hash",
          "named": true
        },
        {
          "type": "cf_if_keyword",
          "named": true
        },
        {
          "type": "cf_operator",
          "named": true
        },
        {
          "type": "cf_parens",
          "named": true
        },
        {
          "type": "cf_period",
          "named": true
        },
        {
          "type": "cf_tag",
          "named": true
        },
        {
          "type": "cf_tag_end",
          "named": true
        },
        {
          "type": "cf_variable",
          "named": true
        },
        {
          "type": "text",
          "named": true
        }
      ]
    }
  },
  {
    "type": "cf_if_end",
    "named": true,
    "fields": {},
    "children": {
      "multiple": true,
      "required": false,
      "types": [
        {
          "type": "cf_if_keyword",
          "named": true
        },
        {
          "type": "cf_tag_close",
          "named": true
        }
      ]
    }
  },
  {
    "type": "cf_ifstatement",
    "named": true,
    "fields": {},
    "children": {
      "multiple": true,
      "required": true,
      "types": [
        {
          "type": "cf_else",
          "named": true
        },
        {
          "type": "cf_elseif",
          "named": true
        },
        {
          "type": "cf_if",
          "named": true
        },
        {
          "type": "cf_if_end",
          "named": true
        }
      ]
    }
  },
  {
    "type": "cf_parens",
    "named": true,
    "fields": {},
    "children": {
      "multiple": true,
      "required": true,
      "types": [
        {
          "type": "cf_assignment",
          "named": true
        },
        {
          "type": "cf_associative",
          "named": true
        },
        {
          "type": "cf_comma",
          "named": true
        },
        {
          "type": "cf_operator",
          "named": true
        },
        {
          "type": "cf_parens",
          "named": true
        },
        {
          "type": "cf_period",
          "named": true
        },
        {
          "type": "cf_variable",
          "named": true
        }
      ]
    }
  },
  {
    "type": "cf_set",
    "named": true,
    "fields": {},
    "children": {
      "multiple": true,
      "required": true,
      "types": [
        {
          "type": "cf_assignment",
          "named": true
        },
        {
          "type": "cf_associative",
          "named": true
        },
        {
          "type": "cf_comma",
          "named": true
        },
        {
          "type": "cf_operator",
          "named": true
        },
        {
          "type": "cf_parens",
          "named": true
        },
        {
          "type": "cf_period",
          "named": true
        },
        {
          "type": "cf_tag_end",
          "named": true
        },
        {
          "type": "cf_variable",
          "named": true
        }
      ]
    }
  },
  {
    "type": "cf_tag",
    "named": true,
    "fields": {},
    "children": {
      "multiple": false,
      "required": true,
      "types": [
        {
          "type": "cf_function",
          "named": true
        },
        {
          "type": "cf_ifstatement",
          "named": true
        },
        {
          "type": "cf_set",
          "named": true
        },
        {
          "type": "cf_tag",
          "named": true
        }
      ]
    }
  },
  {
    "type": "cf_variable",
    "named": true,
    "fields": {}
  },
  {
    "type": "fragment",
    "named": true,
    "fields": {},
    "children": {
      "multiple": true,
      "required": false,
      "types": [
        {
          "type": "cf_associative",
          "named": true
        },
        {
          "type": "cf_hash",
          "named": true
        },
        {
          "type": "cf_parens",
          "named": true
        },
        {
          "type": "cf_tag",
          "named": true
        },
        {
          "type": "text",
          "named": true
        }
      ]
    }
  },
  {
    "type": "quoted_attribute_value",
    "named": true,
    "fields": {},
    "children": {
      "multiple": false,
      "required": false,
      "types": [
        {
          "type": "attribute_value",
          "named": true
        }
      ]
    }
  },
  {
    "type": "text",
    "named": true,
    "fields": {}
  },
  {
    "type": "\"",
    "named": false
  },
  {
    "type": "#",
    "named": false
  },
  {
    "type": "'",
    "named": false
  },
  {
    "type": "(",
    "named": false
  },
  {
    "type": ")",
    "named": false
  },
  {
    "type": "=",
    "named": false
  },
  {
    "type": ">",
    "named": false
  },
  {
    "type": "[",
    "named": false
  },
  {
    "type": "]",
    "named": false
  },
  {
    "type": "attribute_name",
    "named": true
  },
  {
    "type": "attribute_value",
    "named": true
  },
  {
    "type": "cf_comma",
    "named": true
  },
  {
    "type": "cf_else_keyword",
    "named": true
  },
  {
    "type": "cf_elseif_keyword",
    "named": true
  },
  {
    "type": "cf_function_keyword",
    "named": true
  },
  {
    "type": "cf_if_keyword",
    "named": true
  },
  {
    "type": "cf_operator",
    "named": true
  },
  {
    "type": "cf_period",
    "named": true
  },
  {
    "type": "cf_tag_close",
    "named": true
  },
  {
    "type": "cf_tag_end",
    "named": true
  },
  {
    "type": "set",
    "named": false
  },
  {
    "type": "}",
    "named": false
  }
]